Metadata-Version: 2.1
Name: QHrxQuery
Version: 0.0.2
Summary: 内部使用
Home-page: https://gitee.com/lwtyhm/qhrxquery.git
Author: 李文涛
Author-email: 1447914988@qq.com
License: UNKNOWN
Platform: UNKNOWN
Classifier: Programming Language :: Python :: 3
Classifier: License :: OSI Approved :: MIT License
Classifier: Operating System :: OS Independent
Requires-Python: >=3.8
